wineml/__init__.py
wineml-0.0.1.dist-info/LICENSE
wineml-0.0.1.dist-info/WHEEL
wineml-0.0.1.dist-info/METADATA
wineml-0.0.1.dist-info/RECORD
