Metadata-Version: 2.1
Name: wineml
Version: 0.0.1
Summary: Python library for WineML Registry
Author: Melvin Low
Author-email: lowbingjiun@gmail.com
Requires-Python: >=3.9,<4.0
Classifier: Programming Language :: Python :: 3
Classifier: Programming Language :: Python :: 3.9
Classifier: Programming Language :: Python :: 3.10
Classifier: Programming Language :: Python :: 3.11
